anai/__init__.py
anai/preprocessing/__init__.py
anai/preprocessing/statistics/__init__.py
anai/supervised/__init__.py
anai/unsupervised/__init__.py
anai/unsupervised/anomaly_detection/__init__.py
anai/unsupervised/anomaly_detection/configs.py
anai/utils/best.py
anai/utils/configs.py
anai/utils/custom_data_types.py
anai/utils/encoder.py
anai/utils/ensembler.py
anai/utils/plot.py
anai/utils/predictors.py
anai/utils/scaler.py
anai/utils/validator.py
anai/utils/connectors/__init__.py
anai/utils/connectors/data_handler.py
anai/utils/custom_models/wrapped_classifiers.py
anai/utils/explainable_anai/explain_core.py
anai/utils/explainable_anai/permutation.py
anai/utils/explainable_anai/shap.py
anai/utils/explainable_anai/surrogate.py
anai/utils/handlers/dimension_handler.py
anai/utils/tuner/anai_tuner.py
anai/utils/tuner/optuna/optuna_base.py
anai/utils/tuner/optuna/objectives/classification_objectives.py
anai/utils/tuner/optuna/objectives/regression_objectives.py
anai/utils/wrappers/classification_shell.py
anai_opensource-0.1.7.2.dist-info/LICENSE
anai_opensource-0.1.7.2.dist-info/METADATA
anai_opensource-0.1.7.2.dist-info/WHEEL
anai_opensource-0.1.7.2.dist-info/top_level.txt
anai_opensource-0.1.7.2.dist-info/RECORD
