Metadata-Version: 2.1
Name: anai-opensource
Version: 0.1.7.2
Summary: Automated ML
Home-page: https://github.com/Revca-ANAI/ANAI
Author: Revca-ANAI
Author-email: info@anai.io
License: Apache License 2.0
Keywords: ANAI,AutoML,Python
Classifier: Development Status :: 3 - Alpha
Classifier: Intended Audience :: Developers
Classifier: Topic :: Software Development :: Build Tools
Classifier: Programming Language :: Python :: 3
Classifier: Programming Language :: Python :: 3.4
Classifier: Programming Language :: Python :: 3.5
Classifier: Programming Language :: Python :: 3.6
Classifier: Programming Language :: Python :: 3.9
License-File: LICENSE
Requires-Dist: boto3
Requires-Dist: catboost
Requires-Dist: colorama
Requires-Dist: datashape
Requires-Dist: db-dtypes
Requires-Dist: decorator
Requires-Dist: dnspython
Requires-Dist: fuzzywuzzy
Requires-Dist: google-cloud-bigquery
Requires-Dist: google-cloud-bigquery-storage
Requires-Dist: h11
Requires-Dist: imbalanced-learn
Requires-Dist: matplotlib
Requires-Dist: matplotlib-inline
Requires-Dist: networkx
Requires-Dist: numpy
Requires-Dist: optuna
Requires-Dist: pandas
Requires-Dist: pydot
Requires-Dist: pydotplus
Requires-Dist: pymongo
Requires-Dist: pyparsing
Requires-Dist: python-dateutil
Requires-Dist: pytz
Requires-Dist: pytz-deprecation-shim
Requires-Dist: scikit-learn
Requires-Dist: scipy (>=1.5)
Requires-Dist: seaborn
Requires-Dist: shap
Requires-Dist: xgboost
Requires-Dist: yacs
Requires-Dist: pyod
Requires-Dist: modin[all]
Requires-Dist: distributed
Requires-Dist: openpyxl
Requires-Dist: category-encoders
Requires-Dist: snowflake-connector-python
Requires-Dist: snowflake-sqlalchemy
Requires-Dist: mlxtend (==0.20.0)
Requires-Dist: python-Levenshtein ; platform_system == "Linux" or platform_system == "Darwin"
Requires-Dist: lightgbm ; platform_system == "Linux" or platform_system == "Windows"
Requires-Dist: python-Levenshtein-wheels ; platform_system == "Windows"
